saltedge/__init__.py
saltedge/api/__init__.py
saltedge/api/accounts.py
saltedge/api/attempts.py
saltedge/api/connections.py
saltedge/api/countries.py
saltedge/api/customers.py
saltedge/api/lead/__init__.py
saltedge/api/lead/leads.py
saltedge/api/lead/sessions.py
saltedge/api/providers.py
saltedge/api/transactions.py
saltedge/http.py
saltedge/logging.py
saltedge/services.py
saltedge/tests/__init__.py
saltedge-0.1.3.dist-info/LICENSE
saltedge-0.1.3.dist-info/METADATA
saltedge-0.1.3.dist-info/WHEEL
saltedge-0.1.3.dist-info/RECORD
