Metadata-Version: 2.1
Name: saltedge
Version: 0.1.3
Summary: A simple python wrapper around saltedge api with some utilities.
Home-page: https://pypi.org/project/saltedge/
License: apache v2
Author: besil
Author-email: silvio.bernardinello@outlook.com
Requires-Python: >=3.11,<4.0
Classifier: License :: Other/Proprietary License
Classifier: Programming Language :: Python :: 3
Classifier: Programming Language :: Python :: 3.11
Classifier: Programming Language :: Python :: 3.12
Requires-Dist: cryptography (>=42.0.5,<43.0.0)
Requires-Dist: requests (>=2.31.0,<3.0.0)
Project-URL: Repository, https://github.com/besil/saltedge
